storybook_csf/__init__.py
storybook_csf/py.typed
storybook_csf/story.py
storybook_csf-1.0.1.dist-info/licenses/LICENSE
storybook_csf-1.0.1.dist-info/METADATA
storybook_csf-1.0.1.dist-info/WHEEL
storybook_csf-1.0.1.dist-info/top_level.txt
storybook_csf-1.0.1.dist-info/RECORD
