Metadata-Version: 2.4
Name: storybook_csf
Version: 1.0.1
Summary: Write Storybook stories in Python - Typings for Storybook and the Component Story Format (CSF)
Author-email: Juro Oravec <juraj.oravec.josefson@gmail.com>
License: MIT
Project-URL: Homepage, https://github.com/jurooravec/storybook-csf/
Keywords: storybook,server,types,csf
Classifier: Operating System :: OS Independent
Classifier: Programming Language :: Python
Classifier: Programming Language :: Python :: 3
Classifier: Programming Language :: Python :: 3.8
Classifier: Programming Language :: Python :: 3.9
Classifier: Programming Language :: Python :: 3.10
Classifier: Programming Language :: Python :: 3.11
Classifier: Programming Language :: Python :: 3.12
Classifier: Programming Language :: Python :: 3.13
Requires-Python: <4.0,>=3.8
License-File: LICENSE
Dynamic: license-file
